eatable/__init__.py
eatable/coco.py
eatable-0.1.3.dist-info/LICENSE
eatable-0.1.3.dist-info/METADATA
eatable-0.1.3.dist-info/WHEEL
eatable-0.1.3.dist-info/top_level.txt
eatable-0.1.3.dist-info/RECORD
