Metadata-Version: 2.1
Name: eatable
Version: 0.1.3
Summary: Eatable Code
Home-page: https://github.com/eatable-code/eatable
Author: sirius demon
Author-email: mory2016@126.com
License: UNKNOWN
Platform: UNKNOWN
Classifier: Programming Language :: Python :: 3
Classifier: Operating System :: OS Independent
